client/__init__.py
client/auth.py
client/client.py
client/session.py
emoji/__init__.py
emoji/emoji.py
errors/__init__.py
errors/exceptions.py
errors/rpc.py
handlers/__init__.py
handlers/handlers.py
methods/__init__.py
methods/methods.py
network/__init__.py
network/data_center.py
network/encryption.py
network/mtproto_receiver.py
network/mtproto_sender.py
network/shared.py
network/transport.py
parser/__init__.py
parser/generator.py
parser/tl_object.py
parser/tl_parser.py
sessions/__init__.py
sessions/file_session.py
sessions/memory_session.py
types/__init__.py
types/async_helpers.py
types/sync_helpers.py
types/channel/__init__.py
types/channel/channel.py
types/channel/input_channel.py
types/chat/__init__.py
types/chat/chat.py
types/chat/chat_empty.py
types/chat/chat_forbidden.py
types/users/__init__.py
types/users/user.py
utils/__init__.py
utils/binary_reader.py
utils/binary_writer.py
neongram-0.1.4.dist-info/METADATA
neongram-0.1.4.dist-info/WHEEL
neongram-0.1.4.dist-info/top_level.txt
neongram-0.1.4.dist-info/RECORD
